{
  "main": {
    "id": "74951c30261f8aa9",
    "type": "split",
    "children": [
      {
        "id": "b34191bf291ca227",
        "type": "tabs",
        "children": [
          {
            "id": "7003a87e8677b4c4",
            "type": "leaf",
            "state": {
              "type": "kanban",
              "state": {
                "file": "docs/Projektorganisation/Kanban.md"
              }
            }
          },
          {
            "id": "33436ad13987ba3c",
            "type": "leaf",
            "state": {
              "type": "markdown",
              "state": {
                "file": "README.md",
                "mode": "source",
                "source": false
              }
            }
          },
          {
            "id": "b727a3fceeb9bafa",
            "type": "leaf",
            "state": {
              "type": "markdown",
              "state": {
                "file": "Anhang/Quellen.md",
                "mode": "source",
                "source": false
              }
            }
          },
          {
            "id": "2b6ef172f137ee26",
            "type": "leaf",
            "state": {
              "type": "markdown",
              "state": {
                "file": "docs/Aufbau Umgebung/Website.md",
                "mode": "source",
                "source": false
              }
            }
          }
        ],
        "currentTab": 3
      }
    ],
    "direction": "vertical"
  },
  "left": {
    "id": "50bbc040f8139c6b",
    "type": "split",
    "children": [
      {
        "id": "42fdcffeabfa629e",
        "type": "tabs",
        "children": [
          {
            "id": "183855e654b2e479",
            "type": "leaf",
            "state": {
              "type": "file-explorer",
              "state": {
                "sortOrder": "alphabetical"
              }
            }
          },
          {
            "id": "68126cedb5668276",
            "type": "leaf",
            "state": {
              "type": "search",
              "state": {
                "query": "",
                "matchingCase": false,
                "explainSearch": false,
                "collapseAll": false,
                "extraContext": false,
                "sortOrder": "alphabetical"
              }
            }
          },
          {
            "id": "90094b2440c940e7",
            "type": "leaf",
            "state": {
              "type": "bookmarks",
              "state": {}
            }
          }
        ]
      }
    ],
    "direction": "horizontal",
    "width": 300
  },
  "right": {
    "id": "316786353fe8543c",
    "type": "split",
    "children": [
      {
        "id": "70468a3ab2f8425a",
        "type": "tabs",
        "children": [
          {
            "id": "4c7f310c9c64bf38",
            "type": "leaf",
            "state": {
              "type": "backlink",
              "state": {
                "file": "docs/Aufbau Umgebung/Website.md",
                "collapseAll": false,
                "extraContext": false,
                "sortOrder": "alphabetical",
                "showSearch": false,
                "searchQuery": "",
                "backlinkCollapsed": false,
                "unlinkedCollapsed": true
              }
            }
          },
          {
            "id": "9a8e957e1419bca2",
            "type": "leaf",
            "state": {
              "type": "outgoing-link",
              "state": {
                "file": "docs/Aufbau Umgebung/Website.md",
                "linksCollapsed": false,
                "unlinkedCollapsed": true
              }
            }
          },
          {
            "id": "92734e79cb14accc",
            "type": "leaf",
            "state": {
              "type": "tag",
              "state": {
                "sortOrder": "frequency",
                "useHierarchy": true
              }
            }
          },
          {
            "id": "4d60679294afed73",
            "type": "leaf",
            "state": {
              "type": "outline",
              "state": {
                "file": "docs/Aufbau Umgebung/Website.md"
              }
            }
          }
        ]
      }
    ],
    "direction": "horizontal",
    "width": 300,
    "collapsed": true
  },
  "left-ribbon": {
    "hiddenItems": {
      "switcher:Schnellauswahl öffnen": false,
      "graph:Graphen-Ansicht öffnen": false,
      "canvas:Neuen Canvas erstellen": false,
      "daily-notes:Heutige Notiz öffnen": false,
      "templates:Vorlage einfügen": false,
      "command-palette:Befehlspalette öffnen": false,
      "obsidian-advanced-slides:Show Slide Preview": false
    }
  },
  "active": "2b6ef172f137ee26",
  "lastOpenFiles": [
    "docs/Aufbau Umgebung/attachments/Pasted image 20240117154044.png",
    "README.md",
    "docs/Projektorganisation/Kanban.md",
    "Anhang/Quellen.md",
    "code/Upload S3 Flask/upload.py",
    "code/Upload S3 Flask/templates",
    "code/Upload S3 Flask",
    "code/website/Upload S3 Flask",
    "code/website/Upload S3",
    "code/website/Upload 3",
    "docs/Aufbau Umgebung/Website.md",
    "code/website/__pycache__/app.cpython-312.pyc",
    "code/website/__pycache__/test.cpython-312.pyc",
    "code/website/__pycache__",
    "code/website/test.py",
    "docs/Aufbau Umgebung/AWS  Rekognition Gallery.md",
    "code/rekognition-demo-master/static/fonts/glyphicons-halflings-regular.svg",
    "code/rekognition-demo-master/Rekognizion Demo.gif",
    "code/rekognition-demo-master/Solution Diagram.PNG",
    "code/rekognition-demo-master/README.md",
    "docs/Aufbau Umgebung/attachments/Pasted image 20240105215504.png",
    "docs/Aufbau Umgebung/Github Actions.md",
    "Anhang/Recherche.md",
    "docs/Aufbau Umgebung/AWS Rekognition Ersterversuch.md",
    "docs/Aufbau Umgebung/readme.md",
    "docs/Projektorganisation/Sprints/attachments/Pasted image 20231218145222.png",
    "docs/Aufbau Umgebung/attachments/Pasted image 20231127144521.png",
    "docs/Projektorganisation/Sprints/Sprint 1 Abschluss.md",
    "docs/Projektorganisation/Sprints/attachments/Pasted image 20231127141432.png",
    "docs/Aufbau Umgebung/Aufbau AWS Lamda Github Actions.md",
    "docs/Aufbau Umgebung/Aufbau S3.md",
    "docs/Projektorganisation/Sprints/attachments/Pasted image 20231124232701.png",
    "docs/Aufbau Umgebung/attachments/Pasted image 20231124230529.png",
    "etc/1 Test Face Comersion/noah-3.jpg",
    "docs/Projektorganisation/Sprints/Sprint 3 Abschluss.md",
    "docs/Projektorganisation/Sprints/Sprint 2 Abschluss.md",
    "docs/Einleitung/readme.md",
    "docs/Aufbau Umgebung/Aufbau AWS Lamda Gitlab Piplines.md",
    "docs/Aufbau Umgebung/Pasted image 20231115095003.png.md",
    "docs/Projektorganisation/Projektmethode.md",
    "2023-11-06.md"
  ]
}